pyramid_request_schema/__init__.py
pyramid_request_schema/base_schema.py
pyramid_request_schema/deriver.py
pyramid_request_schema/exceptions.py
pyramid_request_schema/tests.py
pyramid_request_schema-1.0.0.dist-info/METADATA
pyramid_request_schema-1.0.0.dist-info/RECORD
pyramid_request_schema-1.0.0.dist-info/WHEEL
pyramid_request_schema-1.0.0.dist-info/top_level.txt
